assets/screenshot.png
auto_portforward/__init__.py
auto_portforward/_version.py
auto_portforward/cli.py
auto_portforward/datatype.py
auto_portforward/ssh_port_forward.py
auto_portforward/tui.py
auto_portforward/utils.py
auto_portforward/process_provider/abstract_provider.py
auto_portforward/process_provider/get_process_with_openports.py
auto_portforward/process_provider/local.py
auto_portforward/process_provider/script_on_remote_machine.py
auto_portforward/process_provider/ssh_remote.py
auto_portforward-0.2.1.dist-info/licenses/LICENSE
auto_portforward-0.2.1.dist-info/METADATA
auto_portforward-0.2.1.dist-info/WHEEL
auto_portforward-0.2.1.dist-info/entry_points.txt
auto_portforward-0.2.1.dist-info/top_level.txt
auto_portforward-0.2.1.dist-info/RECORD
