Metadata-Version: 2.4
Name: auto-portforward
Version: 0.2.1
Summary: Monitor for local or remote opened ports
Author: soraxas
License: MIT License
License-File: LICENSE
Requires-Dist: textual==3.2.0
Provides-Extra: dev
Requires-Dist: build; extra == "dev"
Requires-Dist: dapperdata; extra == "dev"
Requires-Dist: mypy; extra == "dev"
Requires-Dist: pytest; extra == "dev"
Requires-Dist: pytest-asyncio; extra == "dev"
Requires-Dist: pytest-cov; extra == "dev"
Requires-Dist: pytest-pretty; extra == "dev"
Requires-Dist: ruamel.yaml; extra == "dev"
Requires-Dist: ruff; extra == "dev"
Requires-Dist: toml-sort; extra == "dev"
Dynamic: license-file
